europarl/__init__.py
europarl/client.py
europarl-0.1.2.dist-info/LICENSE
europarl-0.1.2.dist-info/METADATA
europarl-0.1.2.dist-info/WHEEL
europarl-0.1.2.dist-info/RECORD
