Metadata-Version: 2.3
Name: europarl
Version: 0.1.2
Summary: A Python HTTP client for accessing and analyzing European Parliament data
License: MIT
Keywords: european parliament,http client,data analysis
Author: robincvlr
Requires-Python: >=3.9,<4.0
Classifier: License :: OSI Approved :: MIT License
Classifier: Programming Language :: Python :: 3
Classifier: Programming Language :: Python :: 3.9
Classifier: Programming Language :: Python :: 3.10
Classifier: Programming Language :: Python :: 3.11
Classifier: Programming Language :: Python :: 3.12
Classifier: Programming Language :: Python :: 3.13
Requires-Dist: aiohttp (>=3.9.5,<4.0.0)
Project-URL: Homepage, https://github.com/robincvlr/europarl
Project-URL: Repository, https://github.com/robincvlr/europarl
